[
    {
        "name": "Иван Иванов",
        "picSrc": "http://www.gravatar.com/avatar/205e460b479e2e5b48aec07710c08d50",
        "bio": "Lorem ipsum dolor sit amet, consectetur adipisicing elit, sed do eiusmod tempor ",
        "id": 1
    },
    {
        "name": "Супер Арсений ",
        "picSrc": "http://www.gravatar.com/avatar/205e460b479e2e5b48aec07710c08d50",
        "bio": "Я ангел ангел ангел ещё что-нибудь",
        "id": 2
    },
    {
        "name": "Ещё один",
        "picSrc": "http://www.gravatar.com/avatar/205e460b479e2e5b48aec07710c08d50",
        "bio": "ещё один тест так так вот так",
        "id": 3
    },
    {
        "name": "кек го кек",
        "bio": "кек пиздато го го норм онлайн",
        "id": 4,
        "picSrc": "http://www.gravatar.com/avatar/205e460b479e2e5b48aec07710c08d50"
    },
    {
        "name": "новый",
        "picSrc": "http://www.gravatar.com/avatar/205e460b479e2e5b48aec07710c08d50",
        "bio": "ахаха меняем",
        "id": 5
    },
    {
        "name": "тест",
        "picSrc": "http://www.gravatar.com/avatar/205e460b479e2e5b48aec07710c08d50",
        "bio": "тест",
        "id": 6
    },
    {
        "name": "хуй хуевич",
        "picSrc": "http://sef",
        "bio": "норм описание",
        "id": 7
    },
    {
        "name": "хуй 2",
        "picSrc": "http://fesf",
        "bio": "srkop",
        "id": 8
    },
    {
        "name": "рлро",
        "picSrc": "http://houh",
        "bio": "hkjhkj",
        "id": 9
    },
    {
        "name": "аыуаы",
        "picSrc": "http://fsef",
        "bio": "ssggseg",
        "id": 10
    },
    {
        "name": "sfej",
        "picSrc": "http://esfs",
        "bio": "srg",
        "id": 11
    },
    {
        "name": "норм",
        "picSrc": "http://efsfs",
        "bio": "куль изменение 4",
        "id": 12
    },
    {
        "name": "one",
        "picSrc": "http://sf",
        "bio": "изменение 5",
        "id": 13
    },
    {
        "name": "one",
        "picSrc": "http://sf",
        "bio": "изменение 5",
        "id": 14
    }
]